setup.py
hana/__init__.py
hana/core.py
hana/errors.py
hana/plugins.py
hana.egg-info/PKG-INFO
hana.egg-info/SOURCES.txt
hana.egg-info/dependency_links.txt
hana.egg-info/top_level.txt
test/test_plugins.py
test/test_simple.py