Metadata-Version: 1.1
Name: hana
Version: 0.0.1
Summary: Static site generator
Home-page: https://github.com/mayo/hana
Author: Mayo Jordanov
Author-email: mayo@oyam.ca
License: MIT
Keywords: hana static site generator processing file
Platform: UNKNOWN
Classifier: Development Status :: 3 - Alpha
Classifier: License :: Other/Proprietary License
Classifier: Programming Language :: Python :: 2
Classifier: Programming Language :: Python :: 3
